karrio/mappers/boxknight/__init__.py
karrio/mappers/boxknight/mapper.py
karrio/mappers/boxknight/proxy.py
karrio/mappers/boxknight/settings.py
karrio/plugins/boxknight/__init__.py
karrio/providers/boxknight/__init__.py
karrio/providers/boxknight/error.py
karrio/providers/boxknight/rate.py
karrio/providers/boxknight/tracking.py
karrio/providers/boxknight/units.py
karrio/providers/boxknight/utils.py
karrio/providers/boxknight/shipment/__init__.py
karrio/providers/boxknight/shipment/cancel.py
karrio/providers/boxknight/shipment/create.py
karrio/schemas/boxknight/__init__.py
karrio/schemas/boxknight/error.py
karrio/schemas/boxknight/order_request.py
karrio/schemas/boxknight/rate_request.py
karrio/schemas/boxknight/rate_response.py
karrio/schemas/boxknight/tracking_response.py
karrio_boxknight-2026.1.4.dist-info/METADATA
karrio_boxknight-2026.1.4.dist-info/WHEEL
karrio_boxknight-2026.1.4.dist-info/entry_points.txt
karrio_boxknight-2026.1.4.dist-info/top_level.txt
karrio_boxknight-2026.1.4.dist-info/RECORD
